{
  "trades": [
    {
      "type": "buy_filled",
      "side": "BUY",
      "price": 4.26,
      "qty": 100,
      "reason": "ENTRY",
      "entry_price": 0,
      "pnl": 0,
      "timestamp": "2026-06-11T12:00:31.645448"
    },
    {
      "type": "sell_filled",
      "side": "SELL",
      "price": 4.19,
      "qty": 100,
      "reason": "SL",
      "entry_price": 4.26,
      "pnl": -7.0,
      "timestamp": "2026-06-12T10:00:39.518379"
    },
    {
      "type": "buy_filled",
      "side": "BUY",
      "price": 4.19,
      "qty": 100,
      "reason": "ENTRY",
      "entry_price": 0,
      "pnl": 0,
      "timestamp": "2026-06-12T10:31:03.299824"
    },
    {
      "type": "sell_filled",
      "side": "SELL",
      "price": 4.28,
      "qty": 100,
      "reason": "TP",
      "entry_price": 4.19,
      "pnl": 9.0,
      "timestamp": "2026-06-19T10:00:39.800293"
    },
    {
      "type": "buy_filled",
      "side": "BUY",
      "price": 4.22,
      "qty": 100,
      "reason": "ENTRY",
      "entry_price": 0,
      "pnl": 0,
      "timestamp": "2026-06-26T09:30:55.062782"
    },
    {
      "type": "sell_filled",
      "side": "SELL",
      "price": 4.32,
      "qty": 100,
      "reason": "TP",
      "entry_price": 4.22,
      "pnl": 10.0,
      "timestamp": "2026-07-06T11:30:29.927194"
    }
  ],
  "last_updated": "2026-07-06T11:30:30.847887",
  "agent": "ioi"
}